intelliscraper/__init__.py
intelliscraper/main.py
intelliscraper/test.py
intelliscraper/utils.py
intelliscraper/web_scraper.py
IntelliScraper-1.0.2.dist-info/LICENSE
IntelliScraper-1.0.2.dist-info/METADATA
IntelliScraper-1.0.2.dist-info/WHEEL
IntelliScraper-1.0.2.dist-info/top_level.txt
IntelliScraper-1.0.2.dist-info/RECORD
