Metadata-Version: 2.1
Name: IntelliScraper
Version: 1.0.2
Summary: An advanced web scraping tool using BeautifulSoup and scikit-learn.
Home-page: https://github.com/herche-jane/IntelliScraper
Author: Herche Jane
Author-email: 524430556@qq.com
License: MIT
Classifier: Programming Language :: Python :: 3
Classifier: License :: OSI Approved :: MIT License
Classifier: Operating System :: OS Independent
License-File: LICENSE
Requires-Dist: beautifulsoup4
Requires-Dist: scikit-learn
Requires-Dist: requests
Requires-Dist: utils
